snowpaw/__init__.py
snowpaw/snowpaw.py
tests/__init__.py
snowpaw-0.0.3.dist-info/LICENSE
snowpaw-0.0.3.dist-info/METADATA
snowpaw-0.0.3.dist-info/WHEEL
snowpaw-0.0.3.dist-info/top_level.txt
snowpaw-0.0.3.dist-info/RECORD
